tra_analysis/Analysis.py
tra_analysis/Array.py
tra_analysis/ClassificationMetric.py
tra_analysis/Clustering.py
tra_analysis/CorrelationTest.py
tra_analysis/Fit.py
tra_analysis/KNN.py
tra_analysis/NaiveBayes.py
tra_analysis/RandomForest.py
tra_analysis/RegressionMetric.py
tra_analysis/SVM.py
tra_analysis/Sort.py
tra_analysis/StatisticalTest.py
tra_analysis/__init__.py
tra_analysis/equation/Expression.py
tra_analysis/equation/__init__.py
tra_analysis/equation/parser/BNF.py
tra_analysis/equation/parser/Hybrid.py
tra_analysis/equation/parser/RegexInplaceParser.py
tra_analysis/equation/parser/__init__.py
tra_analysis/equation/parser/py2.py
tra_analysis/equation/parser/Hybrid_Utils/ExpressionCore.py
tra_analysis/equation/parser/Hybrid_Utils/__init__.py
tra_analysis/equation/parser/Hybrid_Utils/equation_base.py
tra_analysis/equation/parser/Hybrid_Utils/similar.py
tra_analysis/metrics/__init__.py
tra_analysis/metrics/elo.py
tra_analysis/metrics/glicko2.py
tra_analysis/metrics/trueskill.py
tra_analysis-4.0.0.dist-info/METADATA
tra_analysis-4.0.0.dist-info/WHEEL
tra_analysis-4.0.0.dist-info/top_level.txt
tra_analysis-4.0.0.dist-info/RECORD
