Metadata-Version: 2.1
Name: tra-analysis
Version: 4.0.0
Summary: Analysis package developed by Titan Scouting for The Red Alliance
Home-page: https://github.com/titanscout2022/tr2022-strategy
Author: The Titan Scouting Team
Author-email: titanscout2022@gmail.com
License: BSD 3-Clause License
Keywords: data analysis tools
Platform: UNKNOWN
Classifier: Programming Language :: Python :: 3
Classifier: Operating System :: OS Independent
Requires-Python: >=3.6
Requires-Dist: numpy
Requires-Dist: scipy
Requires-Dist: scikit-learn
Requires-Dist: six
Requires-Dist: pyparsing
Requires-Dist: pylint
Requires-Dist: pytest
